lale/__init__.py
lale/docstrings.py
lale/expressions.py
lale/grammar.py
lale/helpers.py
lale/json_operator.py
lale/operator_wrapper.py
lale/operators.py
lale/pretty_print.py
lale/py.typed
lale/schema2enums.py
lale/schema_ranges.py
lale/schema_simplifier.py
lale/schema_utils.py
lale/schemas.py
lale/settings.py
lale/sklearn_compat.py
lale/type_checking.py
lale/visualize.py
lale/datasets/__init__.py
lale/datasets/data_schemas.py
lale/datasets/movie_review.py
lale/datasets/prefetch.py
lale/datasets/sklearn_to_pandas.py
lale/datasets/util.py
lale/datasets/multitable/__init__.py
lale/datasets/multitable/fetch_datasets.py
lale/datasets/multitable/util.py
lale/datasets/openml/__init__.py
lale/datasets/openml/openml_datasets.py
lale/datasets/uci/__init__.py
lale/datasets/uci/uci_datasets.py
lale/lib/__init__.py
lale/lib/_common_schemas.py
lale/lib/dataframe.py
lale/lib/aif360/__init__.py
lale/lib/aif360/_mystic_util.py
lale/lib/aif360/_suppress_aif360_warnings.py
lale/lib/aif360/adversarial_debiasing.py
lale/lib/aif360/bagging_orbis_classifier.py
lale/lib/aif360/calibrated_eq_odds_postprocessing.py
lale/lib/aif360/datasets.py
lale/lib/aif360/disparate_impact_remover.py
lale/lib/aif360/eq_odds_postprocessing.py
lale/lib/aif360/gerry_fair_classifier.py
lale/lib/aif360/lfr.py
lale/lib/aif360/meta_fair_classifier.py
lale/lib/aif360/optim_preproc.py
lale/lib/aif360/orbis.py
lale/lib/aif360/prejudice_remover.py
lale/lib/aif360/protected_attributes_encoder.py
lale/lib/aif360/redacting.py
lale/lib/aif360/reject_option_classification.py
lale/lib/aif360/reweighing.py
lale/lib/aif360/util.py
lale/lib/autogen/__init__.py
lale/lib/autogen/additive_chi2_sampler.py
lale/lib/autogen/ard_regression.py
lale/lib/autogen/bayesian_ridge.py
lale/lib/autogen/bernoulli_nb.py
lale/lib/autogen/bernoulli_rbm.py
lale/lib/autogen/binarizer.py
lale/lib/autogen/birch.py
lale/lib/autogen/calibrated_classifier_cv.py
lale/lib/autogen/cca.py
lale/lib/autogen/complement_nb.py
lale-0.9.2.dist-info/LICENSE.txt
lale-0.9.2.dist-info/METADATA
lale-0.9.2.dist-info/WHEEL
lale-0.9.2.dist-info/top_level.txt
lale-0.9.2.dist-info/RECORD
