Metadata-Version: 2.1
Name: lale
Version: 0.9.2
Summary: Library for Semi-Automated Data Science
Home-page: https://github.com/IBM/lale
Author: Guillaume Baudart, Martin Hirzel, Kiran Kate, Parikshit Ram, Avraham Shinnar
License: Apache License 2.0
Platform: UNKNOWN
Classifier: Development Status :: 5 - Production/Stable
Classifier: Intended Audience :: Developers
Classifier: Intended Audience :: Science/Research
Classifier: License :: OSI Approved :: Apache Software License
Classifier: Operating System :: MacOS
Classifier: Operating System :: Microsoft :: Windows
Classifier: Operating System :: POSIX
Classifier: Operating System :: Unix
Classifier: Programming Language :: Python
Classifier: Programming Language :: Python :: 3
Classifier: Programming Language :: Python :: 3.9
Classifier: Programming Language :: Python :: 3.10
Classifier: Programming Language :: Python :: 3.11
Classifier: Programming Language :: Python :: 3.12
Classifier: Topic :: Software Development
Classifier: Topic :: Scientific/Engineering
Classifier: Topic :: Scientific/Engineering :: Artificial Intelligence
Requires-Python: >=3.9
License-File: LICENSE.txt
Requires-Dist: numpy
Requires-Dist: black>=22.1.0
Requires-Dist: hyperopt<=0.2.7,>=0.2
Requires-Dist: jsonschema<=5
Requires-Dist: jsonsubschema>=0.0.6
Requires-Dist: scikit-learn<1.8.0,>=1.0.0
Requires-Dist: scipy
Requires-Dist: pandas
Requires-Dist: packaging
Requires-Dist: decorator
Requires-Dist: typing-extensions
Provides-Extra: autoai-fairness
Requires-Dist: dill<=0.3.8; extra == "autoai-fairness"
Requires-Dist: mystic<=0.3.9; extra == "autoai-fairness"
Requires-Dist: klepto<=0.2.2; extra == "autoai-fairness"
Requires-Dist: liac-arff>=2.4.0; extra == "autoai-fairness"
Requires-Dist: aif360>=0.5.0; extra == "autoai-fairness"
Requires-Dist: imbalanced-learn; extra == "autoai-fairness"
Requires-Dist: BlackBoxAuditing; extra == "autoai-fairness"
Provides-Extra: dev
Requires-Dist: pre-commit; extra == "dev"
Provides-Extra: fairness
Requires-Dist: mystic; extra == "fairness"
Requires-Dist: liac-arff>=2.4.0; extra == "fairness"
Requires-Dist: aif360>=0.5.0; extra == "fairness"
Requires-Dist: imbalanced-learn; extra == "fairness"
Requires-Dist: BlackBoxAuditing; extra == "fairness"
Provides-Extra: full
Requires-Dist: mystic; extra == "full"
Requires-Dist: graphviz; extra == "full"
Requires-Dist: xgboost<3.1.0; extra == "full"
Requires-Dist: lightgbm<4.7.0; extra == "full"
Requires-Dist: snapml<1.17.0,>=1.7.0rc3; extra == "full"
Requires-Dist: liac-arff>=2.4.0; extra == "full"
Requires-Dist: tensorflow>=2.4.0; extra == "full"
Requires-Dist: numba; extra == "full"
Requires-Dist: aif360>=0.5.0; extra == "full"
Requires-Dist: torch>=1.0; extra == "full"
Requires-Dist: BlackBoxAuditing; extra == "full"
Requires-Dist: imbalanced-learn; extra == "full"
Requires-Dist: cvxpy>=1.0; extra == "full"
Requires-Dist: fairlearn; extra == "full"
Requires-Dist: h5py; extra == "full"
Provides-Extra: test
Requires-Dist: mystic; extra == "test"
Requires-Dist: joblib; extra == "test"
Requires-Dist: ipython<8.8.0; extra == "test"
Requires-Dist: jupyter; extra == "test"
Requires-Dist: graphviz; extra == "test"
Requires-Dist: lxml<5.2.0; extra == "test"
Requires-Dist: sphinx>=5.0.0; extra == "test"
Requires-Dist: sphinx-rtd-theme>=0.5.2; extra == "test"
Requires-Dist: docutils<0.17; extra == "test"
Requires-Dist: m2r2; extra == "test"
Requires-Dist: sphinxcontrib.apidoc; extra == "test"
Requires-Dist: sphinxcontrib-svg2pdfconverter; extra == "test"
Requires-Dist: pytest; extra == "test"
Requires-Dist: pyspark<4.0.0; extra == "test"
Requires-Dist: func-timeout; extra == "test"
Requires-Dist: category-encoders; extra == "test"
Requires-Dist: pynisher==0.6.4; extra == "test"
Provides-Extra: tutorial
Requires-Dist: ipython<8.8.0; extra == "tutorial"
Requires-Dist: jupyter; extra == "tutorial"
Requires-Dist: graphviz; extra == "tutorial"
Requires-Dist: xgboost<=1.5.1; extra == "tutorial"
Requires-Dist: imbalanced-learn; extra == "tutorial"
Requires-Dist: liac-arff>=2.4.0; extra == "tutorial"
Requires-Dist: aif360>=0.5.0; extra == "tutorial"
Requires-Dist: BlackBoxAuditing; extra == "tutorial"
Requires-Dist: typing-extensions; extra == "tutorial"
Requires-Dist: pandas<2.0.0; extra == "tutorial"
